[
    {
        "nick": "janmark",
        "score": 300
    },
    {
        "nick": "siema",
        "score": 220
    },
    {
        "nick": "kamil",
        "score": 0
    },
    {
        "nick": "kamil1",
        "score": 0
    },
    {
        "nick": "kamil123",
        "score": 0
    },
    {
        "nick": "dasd111",
        "score": 0
    },
    {
        "nick": "123kl",
        "score": 0
    },
    {
        "nick": "kamil",
        "score": 680
    },
    {
        "nick": "123123",
        "score": 620
    },
    {
        "nick": "kamil",
        "score": 0
    },
    {
        "nick": "kamil",
        "score": 0
    },
    {
        "nick": "kamil",
        "score": 0
    },
    {
        "nick": "asdasdas",
        "score": 0
    },
    {
        "nick": "kami",
        "score": 0
    },
    {
        "nick": "kami123",
        "score": 0
    },
    {
        "nick": "kamil112",
        "score": 0
    },
    {
        "nick": "kamil12312",
        "score": 0
    },
    {
        "nick": "kami1233",
        "score": 0
    },
    {
        "nick": "kamil1123123",
        "score": 0
    },
    {
        "nick": "siema1",
        "score": 0
    },
    {
        "nick": "asdasdsd",
        "score": 0
    },
    {
        "nick": "kamil2",
        "score": 340
    }
]